{"cameraMode":{"drawMode":0,"name":"Shaded","section":"Shading Mode"},"sceneLighting":false,"audioPlay":false,"sceneViewState":{"m_AlwaysRefresh":false,"showFog":true,"showSkybox":false,"showFlares":true,"showImageEffects":true,"showParticleSystems":true,"showVisualEffectGraphs":true,"m_FxEnabled":true},"in2DMode":false,"pivot":{"x":-9.5367431640625e-7,"y":2.5622506141662599,"z":0.0},"rotation":{"x":0.3615208864212036,"y":-2.8572451696295965e-11,"z":1.108801384042124e-9,"w":0.932364284992218},"size":6.415340423583984,"orthographic":false}